fastapi_authz/__init__.py
fastapi_authz/middleware.py
fastapi_authz-1.0.0.data/data/README.md
fastapi_authz-1.0.0.data/data/requirements.txt
fastapi_authz-1.0.0.dist-info/LICENSE
fastapi_authz-1.0.0.dist-info/METADATA
fastapi_authz-1.0.0.dist-info/WHEEL
fastapi_authz-1.0.0.dist-info/top_level.txt
fastapi_authz-1.0.0.dist-info/RECORD
