Metadata-Version: 2.1
Name: fastapi-authz
Version: 1.0.0
Summary: An authorization middleware for FastAPI that supports ACL, RBAC, ABAC, based on PyCasbin
Home-page: https://github.com/pycasbin/fastapi-authz
Author: Zxilly
Author-email: zhouxinyu1001@gmail.com
License: Apache 2.0
Keywords: fastapi,starlette,middleware,pycasbin,casbin,auth,authz,acl,rbac,abac,access control,authorization,permission
Classifier: Programming Language :: Python :: 3.9
Classifier: Programming Language :: Python :: 3.10
Classifier: Programming Language :: Python :: 3.11
Classifier: Programming Language :: Python :: 3.12
Classifier: License :: OSI Approved :: Apache Software License
Classifier: Operating System :: OS Independent
Requires-Python: >=3.6
License-File: LICENSE
Requires-Dist: casbin
Requires-Dist: fastapi
